shifty/__init__.py
shifty/core.py
shifty/interfaces.py
shifty/wrappers.py
shifty/iterators.py
shifty/action.py
shifty/impls.py
shifty/caller.py
shifty/errors.py
shifty/utils.py
shifty-1.0.8.dist-info/METADATA
shifty-1.0.8.dist-info/WHEEL
shifty-1.0.8.dist-info/RECORD
shifty-1.0.8.dist-info/top_level.txt
shifty-1.0.8.dist-info/metadata.json
shifty-1.0.8.dist-info/DESCRIPTION.rst
