Metadata-Version: 2.0
Name: shifty
Version: 1.0.8
Summary: A pure-python list shifter/wrapper
Home-page: https://bitbucket.org/sys-git/shifty
Author: Francis Horsman
Author-email: francis.horsman@gmail.com
License: GNU General Public License
Keywords: algorithms
Platform: any
Classifier: Development Status :: 5 - Production/Stable
Classifier: Intended Audience :: Developers
Classifier: License :: OSI Approved :: GNU General Public License v3 (GPLv3)
Classifier: Operating System :: OS Independent
Classifier: Programming Language :: Python
Classifier: Topic :: Software Development :: Libraries :: Python Modules
Requires-Dist: six (>=1.9.0)
